{
    "id": 312,
    "node_id": "MDEwOlJlcG9zaXRvcnkzMTI=",
    "name": "django-mptt",
    "full_name": "brosner/django-mptt",
    "private": false,
    "owner": {
        "login": "brosner",
        "id": 124,
        "node_id": "MDQ6VXNlcjEyNA==",
        "avatar_url": "https://avatars3.githubusercontent.com/u/124?v=4",
        "gravatar_id": "",
        "url": "https://api.github.com/users/brosner",
        "html_url": "https://github.com/brosner",
        "followers_url": "https://api.github.com/users/brosner/followers",
        "following_url": "https://api.github.com/users/brosner/following{/other_user}",
        "gists_url": "https://api.github.com/users/brosner/gists{/gist_id}",
        "starred_url": "https://api.github.com/users/brosner/starred{/owner}{/repo}",
        "subscriptions_url": "https://api.github.com/users/brosner/subscriptions",
        "organizations_url": "https://api.github.com/users/brosner/orgs",
        "repos_url": "https://api.github.com/users/brosner/repos",
        "events_url": "https://api.github.com/users/brosner/events{/privacy}",
        "received_events_url": "https://api.github.com/users/brosner/received_events",
        "type": "User",
        "site_admin": false
    },
    "html_url": "https://github.com/brosner/django-mptt",
    "description": "utilities for implementing a modified pre-order traversal tree in django",
    "fork": true,
    "url": "https://api.github.com/repos/brosner/django-mptt",
    "forks_url": "https://api.github.com/repos/brosner/django-mptt/forks",
    "keys_url": "https://api.github.com/repos/brosner/django-mptt/keys{/key_id}",
    "collaborators_url": "https://api.github.com/repos/brosner/django-mptt/collaborators{/collaborator}",
    "teams_url": "https://api.github.com/repos/brosner/django-mptt/teams",
    "hooks_url": "https://api.github.com/repos/brosner/django-mptt/hooks",
    "issue_events_url": "https://api.github.com/repos/brosner/django-mptt/issues/events{/number}",
    "events_url": "https://api.github.com/repos/brosner/django-mptt/events",
    "assignees_url": "https://api.github.com/repos/brosner/django-mptt/assignees{/user}",
    "branches_url": "https://api.github.com/repos/brosner/django-mptt/branches{/branch}",
    "tags_url": "https://api.github.com/repos/brosner/django-mptt/tags",
    "blobs_url": "https://api.github.com/repos/brosner/django-mptt/git/blobs{/sha}",
    "git_tags_url": "https://api.github.com/repos/brosner/django-mptt/git/tags{/sha}",
    "git_refs_url": "https://api.github.com/repos/brosner/django-mptt/git/refs{/sha}",
    "trees_url": "https://api.github.com/repos/brosner/django-mptt/git/trees{/sha}",
    "statuses_url": "https://api.github.com/repos/brosner/django-mptt/statuses/{sha}",
    "languages_url": "https://api.github.com/repos/brosner/django-mptt/languages",
    "stargazers_url": "https://api.github.com/repos/brosner/django-mptt/stargazers",
    "contributors_url": "https://api.github.com/repos/brosner/django-mptt/contributors",
    "subscribers_url": "https://api.github.com/repos/brosner/django-mptt/subscribers",
    "subscription_url": "https://api.github.com/repos/brosner/django-mptt/subscription",
    "commits_url": "https://api.github.com/repos/brosner/django-mptt/commits{/sha}",
    "git_commits_url": "https://api.github.com/repos/brosner/django-mptt/git/commits{/sha}",
    "comments_url": "https://api.github.com/repos/brosner/django-mptt/comments{/number}",
    "issue_comment_url": "https://api.github.com/repos/brosner/django-mptt/issues/comments{/number}",
    "contents_url": "https://api.github.com/repos/brosner/django-mptt/contents/{+path}",
    "compare_url": "https://api.github.com/repos/brosner/django-mptt/compare/{base}...{head}",
    "merges_url": "https://api.github.com/repos/brosner/django-mptt/merges",
    "archive_url": "https://api.github.com/repos/brosner/django-mptt/{archive_format}{/ref}",
    "downloads_url": "https://api.github.com/repos/brosner/django-mptt/downloads",
    "issues_url": "https://api.github.com/repos/brosner/django-mptt/issues{/number}",
    "pulls_url": "https://api.github.com/repos/brosner/django-mptt/pulls{/number}",
    "milestones_url": "https://api.github.com/repos/brosner/django-mptt/milestones{/number}",
    "notifications_url": "https://api.github.com/repos/brosner/django-mptt/notifications{?since,all,participating}",
    "labels_url": "https://api.github.com/repos/brosner/django-mptt/labels{/name}",
    "releases_url": "https://api.github.com/repos/brosner/django-mptt/releases{/id}",
    "deployments_url": "https://api.github.com/repos/brosner/django-mptt/deployments",
    "created_at": "2008-02-06T17:37:55Z",
    "updated_at": "2019-08-13T13:21:21Z",
    "pushed_at": "2010-05-05T02:46:17Z",
    "git_url": "git://github.com/brosner/django-mptt.git",
    "ssh_url": "git@github.com:brosner/django-mptt.git",
    "clone_url": "https://github.com/brosner/django-mptt.git",
    "svn_url": "https://github.com/brosner/django-mptt",
    "homepage": "http://code.google.com/p/django-mptt/",
    "size": 548,
    "stargazers_count": 59,
    "watchers_count": 59,
    "language": "Python",
    "has_issues": true,
    "has_projects": true,
    "has_downloads": true,
    "has_wiki": true,
    "has_pages": false,
    "forks_count": 1,
    "mirror_url": null,
    "archived": false,
    "disabled": false,
    "open_issues_count": 0,
    "license": {
        "key": "other",
        "name": "Other",
        "spdx_id": "NOASSERTION",
        "url": null,
        "node_id": "MDc6TGljZW5zZTA="
    },
    "forks": 1,
    "open_issues": 0,
    "watchers": 59,
    "default_branch": "master",
    "permissions": {
        "admin": false,
        "push": false,
        "pull": true
    },
    "temp_clone_token": "",
    "parent": {
        "id": 875626,
        "node_id": "MDEwOlJlcG9zaXRvcnk4NzU2MjY=",
        "name": "django-mptt",
        "full_name": "django-mptt/django-mptt",
        "private": false,
        "owner": {
            "login": "django-mptt",
            "id": 382393,
            "node_id": "MDEyOk9yZ2FuaXphdGlvbjM4MjM5Mw==",
            "avatar_url": "https://avatars0.githubusercontent.com/u/382393?v=4",
            "gravatar_id": "",
            "url": "https://api.github.com/users/django-mptt",
            "html_url": "https://github.com/django-mptt",
            "followers_url": "https://api.github.com/users/django-mptt/followers",
            "following_url": "https://api.github.com/users/django-mptt/following{/other_user}",
            "gists_url": "https://api.github.com/users/django-mptt/gists{/gist_id}",
            "starred_url": "https://api.github.com/users/django-mptt/starred{/owner}{/repo}",
            "subscriptions_url": "https://api.github.com/users/django-mptt/subscriptions",
            "organizations_url": "https://api.github.com/users/django-mptt/orgs",
            "repos_url": "https://api.github.com/users/django-mptt/repos",
            "events_url": "https://api.github.com/users/django-mptt/events{/privacy}",
            "received_events_url": "https://api.github.com/users/django-mptt/received_events",
            "type": "Organization",
            "site_admin": false
        },
        "html_url": "https://github.com/django-mptt/django-mptt",
        "description": "Utilities for implementing a modified pre-order traversal tree in django.",
        "fork": false,
        "url": "https://api.github.com/repos/django-mptt/django-mptt",
        "forks_url": "https://api.github.com/repos/django-mptt/django-mptt/forks",
        "keys_url": "https://api.github.com/repos/django-mptt/django-mptt/keys{/key_id}",
        "collaborators_url": "https://api.github.com/repos/django-mptt/django-mptt/collaborators{/collaborator}",
        "teams_url": "https://api.github.com/repos/django-mptt/django-mptt/teams",
        "hooks_url": "https://api.github.com/repos/django-mptt/django-mptt/hooks",
        "issue_events_url": "https://api.github.com/repos/django-mptt/django-mptt/issues/events{/number}",
        "events_url": "https://api.github.com/repos/django-mptt/django-mptt/events",
        "assignees_url": "https://api.github.com/repos/django-mptt/django-mptt/assignees{/user}",
        "branches_url": "https://api.github.com/repos/django-mptt/django-mptt/branches{/branch}",
        "tags_url": "https://api.github.com/repos/django-mptt/django-mptt/tags",
        "blobs_url": "https://api.github.com/repos/django-mptt/django-mptt/git/blobs{/sha}",
        "git_tags_url": "https://api.github.com/repos/django-mptt/django-mptt/git/tags{/sha}",
        "git_refs_url": "https://api.github.com/repos/django-mptt/django-mptt/git/refs{/sha}",
        "trees_url": "https://api.github.com/repos/django-mptt/django-mptt/git/trees{/sha}",
        "statuses_url": "https://api.github.com/repos/django-mptt/django-mptt/statuses/{sha}",
        "languages_url": "https://api.github.com/repos/django-mptt/django-mptt/languages",
        "stargazers_url": "https://api.github.com/repos/django-mptt/django-mptt/stargazers",
        "contributors_url": "https://api.github.com/repos/django-mptt/django-mptt/contributors",
        "subscribers_url": "https://api.github.com/repos/django-mptt/django-mptt/subscribers",
        "subscription_url": "https://api.github.com/repos/django-mptt/django-mptt/subscription",
        "commits_url": "https://api.github.com/repos/django-mptt/django-mptt/commits{/sha}",
        "git_commits_url": "https://api.github.com/repos/django-mptt/django-mptt/git/commits{/sha}",
        "comments_url": "https://api.github.com/repos/django-mptt/django-mptt/comments{/number}",
        "issue_comment_url": "https://api.github.com/repos/django-mptt/django-mptt/issues/comments{/number}",
        "contents_url": "https://api.github.com/repos/django-mptt/django-mptt/contents/{+path}",
        "compare_url": "https://api.github.com/repos/django-mptt/django-mptt/compare/{base}...{head}",
        "merges_url": "https://api.github.com/repos/django-mptt/django-mptt/merges",
        "archive_url": "https://api.github.com/repos/django-mptt/django-mptt/{archive_format}{/ref}",
        "downloads_url": "https://api.github.com/repos/django-mptt/django-mptt/downloads",
        "issues_url": "https://api.github.com/repos/django-mptt/django-mptt/issues{/number}",
        "pulls_url": "https://api.github.com/repos/django-mptt/django-mptt/pulls{/number}",
        "milestones_url": "https://api.github.com/repos/django-mptt/django-mptt/milestones{/number}",
        "notifications_url": "https://api.github.com/repos/django-mptt/django-mptt/notifications{?since,all,participating}",
        "labels_url": "https://api.github.com/repos/django-mptt/django-mptt/labels{/name}",
        "releases_url": "https://api.github.com/repos/django-mptt/django-mptt/releases{/id}",
        "deployments_url": "https://api.github.com/repos/django-mptt/django-mptt/deployments",
        "created_at": "2010-08-31T19:12:55Z",
        "updated_at": "2020-09-26T01:38:08Z",
        "pushed_at": "2020-09-07T14:25:02Z",
        "git_url": "git://github.com/django-mptt/django-mptt.git",
        "ssh_url": "git@github.com:django-mptt/django-mptt.git",
        "clone_url": "https://github.com/django-mptt/django-mptt.git",
        "svn_url": "https://github.com/django-mptt/django-mptt",
        "homepage": "https://django-mptt.readthedocs.io/",
        "size": 2050,
        "stargazers_count": 2362,
        "watchers_count": 2362,
        "language": "Python",
        "has_issues": true,
        "has_projects": true,
        "has_downloads": true,
        "has_wiki": true,
        "has_pages": false,
        "forks_count": 408,
        "mirror_url": null,
        "archived": false,
        "disabled": false,
        "open_issues_count": 102,
        "license": {
            "key": "other",
            "name": "Other",
            "spdx_id": "NOASSERTION",
            "url": null,
            "node_id": "MDc6TGljZW5zZTA="
        },
        "forks": 408,
        "open_issues": 102,
        "watchers": 2362,
        "default_branch": "master"
    },
    "source": {
        "id": 875626,
        "node_id": "MDEwOlJlcG9zaXRvcnk4NzU2MjY=",
        "name": "django-mptt",
        "full_name": "django-mptt/django-mptt",
        "private": false,
        "owner": {
            "login": "django-mptt",
            "id": 382393,
            "node_id": "MDEyOk9yZ2FuaXphdGlvbjM4MjM5Mw==",
            "avatar_url": "https://avatars0.githubusercontent.com/u/382393?v=4",
            "gravatar_id": "",
            "url": "https://api.github.com/users/django-mptt",
            "html_url": "https://github.com/django-mptt",
            "followers_url": "https://api.github.com/users/django-mptt/followers",
            "following_url": "https://api.github.com/users/django-mptt/following{/other_user}",
            "gists_url": "https://api.github.com/users/django-mptt/gists{/gist_id}",
            "starred_url": "https://api.github.com/users/django-mptt/starred{/owner}{/repo}",
            "subscriptions_url": "https://api.github.com/users/django-mptt/subscriptions",
            "organizations_url": "https://api.github.com/users/django-mptt/orgs",
            "repos_url": "https://api.github.com/users/django-mptt/repos",
            "events_url": "https://api.github.com/users/django-mptt/events{/privacy}",
            "received_events_url": "https://api.github.com/users/django-mptt/received_events",
            "type": "Organization",
            "site_admin": false
        },
        "html_url": "https://github.com/django-mptt/django-mptt",
        "description": "Utilities for implementing a modified pre-order traversal tree in django.",
        "fork": false,
        "url": "https://api.github.com/repos/django-mptt/django-mptt",
        "forks_url": "https://api.github.com/repos/django-mptt/django-mptt/forks",
        "keys_url": "https://api.github.com/repos/django-mptt/django-mptt/keys{/key_id}",
        "collaborators_url": "https://api.github.com/repos/django-mptt/django-mptt/collaborators{/collaborator}",
        "teams_url": "https://api.github.com/repos/django-mptt/django-mptt/teams",
        "hooks_url": "https://api.github.com/repos/django-mptt/django-mptt/hooks",
        "issue_events_url": "https://api.github.com/repos/django-mptt/django-mptt/issues/events{/number}",
        "events_url": "https://api.github.com/repos/django-mptt/django-mptt/events",
        "assignees_url": "https://api.github.com/repos/django-mptt/django-mptt/assignees{/user}",
        "branches_url": "https://api.github.com/repos/django-mptt/django-mptt/branches{/branch}",
        "tags_url": "https://api.github.com/repos/django-mptt/django-mptt/tags",
        "blobs_url": "https://api.github.com/repos/django-mptt/django-mptt/git/blobs{/sha}",
        "git_tags_url": "https://api.github.com/repos/django-mptt/django-mptt/git/tags{/sha}",
        "git_refs_url": "https://api.github.com/repos/django-mptt/django-mptt/git/refs{/sha}",
        "trees_url": "https://api.github.com/repos/django-mptt/django-mptt/git/trees{/sha}",
        "statuses_url": "https://api.github.com/repos/django-mptt/django-mptt/statuses/{sha}",
        "languages_url": "https://api.github.com/repos/django-mptt/django-mptt/languages",
        "stargazers_url": "https://api.github.com/repos/django-mptt/django-mptt/stargazers",
        "contributors_url": "https://api.github.com/repos/django-mptt/django-mptt/contributors",
        "subscribers_url": "https://api.github.com/repos/django-mptt/django-mptt/subscribers",
        "subscription_url": "https://api.github.com/repos/django-mptt/django-mptt/subscription",
        "commits_url": "https://api.github.com/repos/django-mptt/django-mptt/commits{/sha}",
        "git_commits_url": "https://api.github.com/repos/django-mptt/django-mptt/git/commits{/sha}",
        "comments_url": "https://api.github.com/repos/django-mptt/django-mptt/comments{/number}",
        "issue_comment_url": "https://api.github.com/repos/django-mptt/django-mptt/issues/comments{/number}",
        "contents_url": "https://api.github.com/repos/django-mptt/django-mptt/contents/{+path}",
        "compare_url": "https://api.github.com/repos/django-mptt/django-mptt/compare/{base}...{head}",
        "merges_url": "https://api.github.com/repos/django-mptt/django-mptt/merges",
        "archive_url": "https://api.github.com/repos/django-mptt/django-mptt/{archive_format}{/ref}",
        "downloads_url": "https://api.github.com/repos/django-mptt/django-mptt/downloads",
        "issues_url": "https://api.github.com/repos/django-mptt/django-mptt/issues{/number}",
        "pulls_url": "https://api.github.com/repos/django-mptt/django-mptt/pulls{/number}",
        "milestones_url": "https://api.github.com/repos/django-mptt/django-mptt/milestones{/number}",
        "notifications_url": "https://api.github.com/repos/django-mptt/django-mptt/notifications{?since,all,participating}",
        "labels_url": "https://api.github.com/repos/django-mptt/django-mptt/labels{/name}",
        "releases_url": "https://api.github.com/repos/django-mptt/django-mptt/releases{/id}",
        "deployments_url": "https://api.github.com/repos/django-mptt/django-mptt/deployments",
        "created_at": "2010-08-31T19:12:55Z",
        "updated_at": "2020-09-26T01:38:08Z",
        "pushed_at": "2020-09-07T14:25:02Z",
        "git_url": "git://github.com/django-mptt/django-mptt.git",
        "ssh_url": "git@github.com:django-mptt/django-mptt.git",
        "clone_url": "https://github.com/django-mptt/django-mptt.git",
        "svn_url": "https://github.com/django-mptt/django-mptt",
        "homepage": "https://django-mptt.readthedocs.io/",
        "size": 2050,
        "stargazers_count": 2362,
        "watchers_count": 2362,
        "language": "Python",
        "has_issues": true,
        "has_projects": true,
        "has_downloads": true,
        "has_wiki": true,
        "has_pages": false,
        "forks_count": 408,
        "mirror_url": null,
        "archived": false,
        "disabled": false,
        "open_issues_count": 102,
        "license": {
            "key": "other",
            "name": "Other",
            "spdx_id": "NOASSERTION",
            "url": null,
            "node_id": "MDc6TGljZW5zZTA="
        },
        "forks": 408,
        "open_issues": 102,
        "watchers": 2362,
        "default_branch": "master"
    },
    "network_count": 408,
    "subscribers_count": 2
}